xai/Random_Forest_model.joblib
xai/XGB_model.joblib
xai/__init__.py
xai/coling.csv
xai/core.py
xai/test.py
xai/utils.py
xai_text_classifier-0.1.3.2.6.dist-info/licenses/LICENSE
xai_text_classifier-0.1.3.2.6.dist-info/METADATA
xai_text_classifier-0.1.3.2.6.dist-info/WHEEL
xai_text_classifier-0.1.3.2.6.dist-info/top_level.txt
xai_text_classifier-0.1.3.2.6.dist-info/RECORD
