Metadata-Version: 2.4
Name: xai-text-classifier
Version: 0.1.3.2.6
Summary: A library to explain whether text is AI-generated or human-written using SHAP
Author-email: Your Name <your.email@example.com>
License: MIT License
Keywords: AI,text-classification,explainability,SHAP
Classifier: Development Status :: 3 - Alpha
Classifier: Intended Audience :: Developers
Classifier: License :: OSI Approved :: MIT License
Classifier: Programming Language :: Python :: 3
Classifier: Programming Language :: Python :: 3.8
Classifier: Programming Language :: Python :: 3.9
Classifier: Programming Language :: Python :: 3.10
Classifier: Programming Language :: Python :: 3.11
Requires-Python: >=3.8
License-File: LICENSE
Requires-Dist: joblib
Requires-Dist: shap
Requires-Dist: xgboost
Requires-Dist: spacy
Requires-Dist: language-tool-python
Requires-Dist: textblob
Requires-Dist: pandas
Requires-Dist: numpy
Requires-Dist: scikit-learn
Requires-Dist: nltk
Requires-Dist: textstat
Requires-Dist: matplotlib
Requires-Dist: scipy
Requires-Dist: textstat
Provides-Extra: dev
Requires-Dist: pytest; extra == "dev"
Requires-Dist: black; extra == "dev"
Requires-Dist: flake8; extra == "dev"
Dynamic: license-file
